nbt.py
PythoNBT-0.1.0.dist-info/LICENSE
PythoNBT-0.1.0.dist-info/METADATA
PythoNBT-0.1.0.dist-info/WHEEL
PythoNBT-0.1.0.dist-info/top_level.txt
PythoNBT-0.1.0.dist-info/RECORD
