Metadata-Version: 2.1
Name: PythoNBT
Version: 0.1.0
Summary: Named Binary Tag (NBT) library
Author-email: Olivia Ryan <olivia.r.dev@gmail.com>
License: MIT License
Classifier: Development Status :: 4 - Beta
Classifier: Topic :: Games/Entertainment
Classifier: License :: OSI Approved :: MIT License
Classifier: Programming Language :: Python :: 3
Classifier: Programming Language :: Python :: 3.10
Classifier: Programming Language :: Python :: 3.11
Classifier: Programming Language :: Python :: 3.12
Requires-Python: >=3.10
License-File: LICENSE
Requires-Dist: netstruct >=1.1.2
